[
  {
    "time": "2026-06-09T13:32:45.741570",
    "text": "ee was played with. Happiness: 64"
  },
  {
    "time": "2026-06-09T13:32:47.490279",
    "text": "ee was cleaned. Energy: 98"
  },
  {
    "time": "2026-06-09T13:33:08.528160",
    "text": "ee was played with. Happiness: 71"
  },
  {
    "time": "2026-06-09T13:33:11.153349",
    "text": "ee was fed. Hunger: 27"
  },
  {
    "time": "2026-06-09T13:33:11.576501",
    "text": "ee was played with. Happiness: 76"
  },
  {
    "time": "2026-06-09T13:33:12.770550",
    "text": "ee was cleaned. "
  },
  {
    "time": "2026-06-09T13:33:13.236509",
    "text": "ee was healed. Health: 88"
  },
  {
    "time": "2026-06-09T13:45:07.032146",
    "text": "ss was healed. Health: 70"
  },
  {
    "time": "2026-06-09T13:45:07.800785",
    "text": "ss was cleaned. Energy: 70"
  },
  {
    "time": "2026-06-09T13:45:10.270758",
    "text": "ss was played with. Happiness: 49"
  },
  {
    "time": "2026-06-09T13:45:10.415664",
    "text": "ss was played with. Happiness: 64"
  },
  {
    "time": "2026-06-09T13:45:10.600370",
    "text": "ss was played with. Happiness: 79"
  },
  {
    "time": "2026-06-09T13:45:11.134281",
    "text": "ss was played with. Happiness: 94"
  },
  {
    "time": "2026-06-09T13:45:12.220221",
    "text": "ss was fed. Hunger: 33"
  },
  {
    "time": "2026-06-09T13:45:12.360168",
    "text": "ss was fed. Hunger: 48"
  },
  {
    "time": "2026-06-09T13:45:12.553827",
    "text": "ss was fed. Hunger: 63"
  },
  {
    "time": "2026-06-09T13:45:12.839763",
    "text": "ss was fed. Hunger: 78"
  },
  {
    "time": "2026-06-09T13:45:13.273640",
    "text": "ss was fed. Hunger: 93"
  },
  {
    "time": "2026-06-09T13:45:13.568053",
    "text": "ss was fed. Hunger: 100"
  },
  {
    "time": "2026-06-09T13:45:13.807417",
    "text": "ss was fed. "
  },
  {
    "time": "2026-06-09T13:45:22.602497",
    "text": "ss was healed. Health: 100"
  },
  {
    "time": "2026-06-09T13:45:23.097055",
    "text": "ss was healed. "
  },
  {
    "time": "2026-06-09T13:45:39.869480",
    "text": "ww was healed. Health: 100"
  },
  {
    "time": "2026-06-09T13:45:40.305062",
    "text": "ww was healed. "
  },
  {
    "time": "2026-06-09T13:45:40.678371",
    "text": "ww was healed. "
  },
  {
    "time": "2026-06-09T13:45:40.899295",
    "text": "ww was healed. "
  },
  {
    "time": "2026-06-09T13:45:41.782378",
    "text": "ww was cleaned. Energy: 100"
  },
  {
    "time": "2026-06-09T13:45:41.991884",
    "text": "ww was cleaned. Energy: 100"
  },
  {
    "time": "2026-06-09T13:45:42.172088",
    "text": "ww was cleaned. "
  },
  {
    "time": "2026-06-09T13:45:43.501783",
    "text": "ww was played with. Happiness: 100"
  },
  {
    "time": "2026-06-09T13:45:43.705635",
    "text": "ww was played with. "
  },
  {
    "time": "2026-06-09T13:45:43.899773",
    "text": "ww was played with. "
  },
  {
    "time": "2026-06-09T13:45:44.097763",
    "text": "ww was played with. "
  },
  {
    "time": "2026-06-09T13:45:44.325895",
    "text": "ww was played with. "
  },
  {
    "time": "2026-06-09T13:45:44.551424",
    "text": "ww was played with. "
  },
  {
    "time": "2026-06-09T14:13:28.850356",
    "text": "dd was healed. Health: 70"
  },
  {
    "time": "2026-06-09T14:13:29.431474",
    "text": "dd was healed. Health: 90"
  },
  {
    "time": "2026-06-09T14:13:29.859769",
    "text": "dd was healed. Health: 100"
  },
  {
    "time": "2026-06-09T14:13:33.772004",
    "text": "dd was played with. Happiness: 49"
  },
  {
    "time": "2026-06-09T14:13:33.959964",
    "text": "dd was played with. Happiness: 64"
  },
  {
    "time": "2026-06-09T14:13:34.193584",
    "text": "dd was played with. Happiness: 79"
  },
  {
    "time": "2026-06-09T14:13:34.728378",
    "text": "dd was played with. Happiness: 94"
  },
  {
    "time": "2026-06-09T14:13:35.284606",
    "text": "dd was played with. Happiness: 100"
  },
  {
    "time": "2026-06-09T14:13:37.546871",
    "text": "dd was cleaned. "
  },
  {
    "time": "2026-06-09T14:13:37.734699",
    "text": "dd was cleaned. "
  },
  {
    "time": "2026-06-09T14:13:37.938741",
    "text": "dd was cleaned. "
  },
  {
    "time": "2026-06-09T14:13:39.212625",
    "text": "dd was fed. Hunger: 15"
  },
  {
    "time": "2026-06-09T14:13:39.371842",
    "text": "dd was fed. Hunger: 30"
  },
  {
    "time": "2026-06-09T14:13:39.634307",
    "text": "dd was fed. Hunger: 45"
  },
  {
    "time": "2026-06-09T14:13:39.887536",
    "text": "dd was fed. Hunger: 60"
  },
  {
    "time": "2026-06-09T14:13:40.130512",
    "text": "dd was fed. Hunger: 75"
  },
  {
    "time": "2026-06-09T14:13:40.386031",
    "text": "dd was fed. Hunger: 90"
  },
  {
    "time": "2026-06-09T14:13:40.698886",
    "text": "dd was fed. Hunger: 100"
  },
  {
    "time": "2026-06-09T14:13:40.877165",
    "text": "dd was fed. "
  },
  {
    "time": "2026-06-09T14:13:42.237117",
    "text": "dd was played with. Happiness: 100"
  },
  {
    "time": "2026-06-09T14:13:42.440693",
    "text": "dd was played with. "
  },
  {
    "time": "2026-06-09T14:13:44.458834",
    "text": "dd was cleaned. "
  },
  {
    "time": "2026-06-09T14:13:45.047744",
    "text": "dd was healed. "
  },
  {
    "time": "2026-06-09T14:16:05.002905",
    "text": "www was cleaned. Energy: 70"
  },
  {
    "time": "2026-06-09T14:16:05.461328",
    "text": "www was cleaned. Energy: 89"
  },
  {
    "time": "2026-06-09T14:16:05.774299",
    "text": "www was cleaned. Energy: 100"
  },
  {
    "time": "2026-06-09T14:16:06.086774",
    "text": "www was cleaned. "
  },
  {
    "time": "2026-06-09T14:16:06.601947",
    "text": "www was cleaned. "
  },
  {
    "time": "2026-06-09T14:16:06.883435",
    "text": "www was cleaned. "
  },
  {
    "time": "2026-06-09T14:16:07.361989",
    "text": "www was cleaned. "
  },
  {
    "time": "2026-06-09T14:16:07.519654",
    "text": "www was cleaned. "
  },
  {
    "time": "2026-06-09T14:16:09.079410",
    "text": "www was played with. Happiness: 64"
  },
  {
    "time": "2026-06-09T14:16:09.639556",
    "text": "www was played with. Happiness: 79"
  },
  {
    "time": "2026-06-09T14:16:09.978952",
    "text": "www was played with. Happiness: 94"
  },
  {
    "time": "2026-06-09T14:16:10.303075",
    "text": "www was played with. Happiness: 100"
  },
  {
    "time": "2026-06-09T14:16:13.107276",
    "text": "www was healed. Health: 89"
  },
  {
    "time": "2026-06-09T14:16:13.306249",
    "text": "www was healed. Health: 100"
  },
  {
    "time": "2026-06-09T14:16:13.579879",
    "text": "www was healed. "
  },
  {
    "time": "2026-06-09T14:16:13.793832",
    "text": "www was healed. "
  },
  {
    "time": "2026-06-09T14:16:14.070711",
    "text": "www was healed. "
  },
  {
    "time": "2026-06-09T14:16:15.112967",
    "text": "www was fed. Hunger: 21"
  },
  {
    "time": "2026-06-09T14:16:15.407188",
    "text": "www was fed. Hunger: 36"
  },
  {
    "time": "2026-06-09T14:16:15.693761",
    "text": "www was fed. Hunger: 51"
  },
  {
    "time": "2026-06-09T14:16:15.948422",
    "text": "www was fed. Hunger: 66"
  },
  {
    "time": "2026-06-09T14:16:16.202700",
    "text": "www was fed. Hunger: 81"
  },
  {
    "time": "2026-06-09T14:16:16.511053",
    "text": "www was fed. Hunger: 96"
  },
  {
    "time": "2026-06-09T14:16:17.223830",
    "text": "www was fed. Hunger: 100"
  },
  {
    "time": "2026-06-09T14:41:40.893582",
    "text": "nnn was healed. Health: 69"
  },
  {
    "time": "2026-06-09T14:41:41.264816",
    "text": "nnn was cleaned. Energy: 69"
  },
  {
    "time": "2026-06-09T14:41:42.116410",
    "text": "nnn was played with. Happiness: 59"
  },
  {
    "time": "2026-06-09T14:41:42.547897",
    "text": "nnn was fed. Hunger: 53"
  },
  {
    "time": "2026-06-09T14:41:42.947042",
    "text": "nnn was played with. Happiness: 74"
  },
  {
    "time": "2026-06-09T14:41:43.681309",
    "text": "nnn was healed. Health: 94"
  },
  {
    "time": "2026-06-09T14:42:12.793340",
    "text": "hi was healed. Health: 70"
  },
  {
    "time": "2026-06-09T14:42:12.957329",
    "text": "hi was cleaned. Energy: 70"
  },
  {
    "time": "2026-06-09T14:42:13.790210",
    "text": "hi was played with. Happiness: 60"
  },
  {
    "time": "2026-06-09T14:42:14.183225",
    "text": "hi was played with. Happiness: 75"
  },
  {
    "time": "2026-06-09T14:42:14.867076",
    "text": "hi was cleaned. "
  },
  {
    "time": "2026-06-09T15:44:01.970951",
    "text": "ni was cleaned. Energy: 70"
  },
  {
    "time": "2026-06-09T15:44:02.225628",
    "text": "ni was cleaned. Energy: 90"
  },
  {
    "time": "2026-06-09T15:44:02.431059",
    "text": "ni was cleaned. Energy: 100"
  },
  {
    "time": "2026-06-09T15:44:02.574370",
    "text": "ni was cleaned. "
  },
  {
    "time": "2026-06-09T15:44:02.945844",
    "text": "ni was cleaned. "
  },
  {
    "time": "2026-06-09T16:02:42.501866",
    "text": "sss was healed. Health: 70"
  }
]